see19/__init__.py
see19/base.py
see19/charts.py
see19/constants.py
see19/helpers.py
see19-0.3.5.dist-info/LICENSE.md
see19-0.3.5.dist-info/METADATA
see19-0.3.5.dist-info/WHEEL
see19-0.3.5.dist-info/top_level.txt
see19-0.3.5.dist-info/RECORD
