Metadata-Version: 2.1
Name: see19
Version: 0.3.5
Summary: An interface for visualizing and analysing the see19 dataset
Home-page: https://github.com/ryanskene/see19
Author: Ryan Skene
Author-email: rjskene83@gmail.com
License: UNKNOWN
Platform: UNKNOWN
Classifier: Programming Language :: Python :: 3.7
Classifier: License :: OSI Approved :: GNU General Public License v3 or later (GPLv3+)
Classifier: Operating System :: OS Independent
Requires-Python: >=3.7
Requires-Dist: bokeh (>=2.0.0)
Requires-Dist: matplotlib (>=3.2.0)
Requires-Dist: numpy (>=1.18.0)
Requires-Dist: pandas (>=1.0.0)
Requires-Dist: requests (>=2.23.0)
